plugable/__init__.py
plugable/class_registry.py
plugable/plugable_meta.py
plugable-1.2.2.dist-info/LICENSE
plugable-1.2.2.dist-info/WHEEL
plugable-1.2.2.dist-info/METADATA
plugable-1.2.2.dist-info/RECORD
