Metadata-Version: 2.1
Name: plugable
Version: 1.2.2
Summary: A framework for writing extensible Python components
License: MIT
Author: Jacob Neil Taylor
Author-email: me@jacobtaylor.id.au
Requires-Python: >=3.8,<4.0
Classifier: License :: OSI Approved :: MIT License
Classifier: Programming Language :: Python :: 3
Classifier: Programming Language :: Python :: 3.8
Classifier: Programming Language :: Python :: 3.9
Classifier: Programming Language :: Python :: 3.10
